newscatcher/__init__.py
newscatcher/aggregation/__init__.py
newscatcher/aggregation/client.py
newscatcher/aggregation/raw_client.py
newscatcher/aggregation/types/__init__.py
newscatcher/aggregation/types/aggregation_get_request_published_date_precision.py
newscatcher/aggregation/types/aggregation_get_request_sort_by.py
newscatcher/aggregation/types/aggregation_get_response.py
newscatcher/aggregation/types/aggregation_post_response.py
newscatcher/authors/__init__.py
newscatcher/authors/client.py
newscatcher/authors/raw_client.py
newscatcher/authors/types/__init__.py
newscatcher/authors/types/authors_get_request_published_date_precision.py
newscatcher/authors/types/authors_get_request_sort_by.py
newscatcher/authors/types/authors_get_response.py
newscatcher/authors/types/authors_post_response.py
newscatcher/base_client.py
newscatcher/breaking_news/__init__.py
newscatcher/breaking_news/client.py
newscatcher/breaking_news/raw_client.py
newscatcher/breaking_news/types/__init__.py
newscatcher/breaking_news/types/breaking_news_get_request_sort_by.py
newscatcher/client.py
newscatcher/core/__init__.py
newscatcher/core/api_error.py
newscatcher/core/client_wrapper.py
newscatcher/core/datetime_utils.py
newscatcher/core/file.py
newscatcher/core/force_multipart.py
newscatcher/core/http_client.py
newscatcher/core/http_response.py
newscatcher/core/jsonable_encoder.py
newscatcher/core/pydantic_utilities.py
newscatcher/core/query_encoder.py
newscatcher/core/remove_none_from_dict.py
newscatcher/core/request_options.py
newscatcher/core/serialization.py
newscatcher/environment.py
newscatcher/errors/__init__.py
newscatcher/errors/bad_request_error.py
newscatcher/errors/forbidden_error.py
newscatcher/errors/internal_server_error.py
newscatcher/errors/request_timeout_error.py
newscatcher/errors/too_many_requests_error.py
newscatcher/errors/unauthorized_error.py
newscatcher/errors/unprocessable_entity_error.py
newscatcher/latestheadlines/__init__.py
newscatcher/latestheadlines/client.py
newscatcher_sdk-1.4.0.dist-info/LICENSE
newscatcher_sdk-1.4.0.dist-info/METADATA
newscatcher_sdk-1.4.0.dist-info/WHEEL
newscatcher_sdk-1.4.0.dist-info/RECORD
